{
	"cmake" : 
	{
		"generator" : 
		{
			"multiConfig" : false,
			"name" : "Ninja"
		},
		"paths" : 
		{
			"cmake" : "/home/arumakan/QT1/Tools/CMake/bin/cmake",
			"cpack" : "/home/arumakan/QT1/Tools/CMake/bin/cpack",
			"ctest" : "/home/arumakan/QT1/Tools/CMake/bin/ctest",
			"root" : "/home/arumakan/QT1/Tools/CMake/share/cmake-3.30"
		},
		"version" : 
		{
			"isDirty" : false,
			"major" : 3,
			"minor" : 30,
			"patch" : 5,
			"string" : "3.30.5",
			"suffix" : ""
		}
	},
	"objects" : 
	[
		{
			"jsonFile" : "codemodel-v2-52d49f6c5ce0cf1bc942.json",
			"kind" : "codemodel",
			"version" : 
			{
				"major" : 2,
				"minor" : 7
			}
		},
		{
			"jsonFile" : "cache-v2-302fad4bb451f96df29e.json",
			"kind" : "cache",
			"version" : 
			{
				"major" : 2,
				"minor" : 0
			}
		},
		{
			"jsonFile" : "cmakeFiles-v1-38812991e6d0dd28d77b.json",
			"kind" : "cmakeFiles",
			"version" : 
			{
				"major" : 1,
				"minor" : 1
			}
		}
	],
	"reply" : 
	{
		"cache-v2" : 
		{
			"jsonFile" : "cache-v2-302fad4bb451f96df29e.json",
			"kind" : "cache",
			"version" : 
			{
				"major" : 2,
				"minor" : 0
			}
		},
		"cmakeFiles-v1" : 
		{
			"jsonFile" : "cmakeFiles-v1-38812991e6d0dd28d77b.json",
			"kind" : "cmakeFiles",
			"version" : 
			{
				"major" : 1,
				"minor" : 1
			}
		},
		"codemodel-v2" : 
		{
			"jsonFile" : "codemodel-v2-52d49f6c5ce0cf1bc942.json",
			"kind" : "codemodel",
			"version" : 
			{
				"major" : 2,
				"minor" : 7
			}
		}
	}
}
